{
  "xgb": {
    "classes": [
      "account_farmer",
      "normal",
      "prompt_sprayer",
      "spam_bot",
      "token_thief"
    ],
    "n_test": 6000,
    "per_class_pr_auc": {
      "account_farmer": 0.9999,
      "normal": 0.9996,
      "prompt_sprayer": 0.9486,
      "spam_bot": 0.9908,
      "token_thief": 1.0
    },
    "abuse_pr_auc": 0.9904,
    "precision_at_k": {
      "100": 1.0,
      "500": 0.94,
      "1000": 0.477
    },
    "abuse_pr_auc_by_evasion": {
      "0.00-0.33": 0.9989,
      "0.33-0.66": 0.9894,
      "0.66-1.01": 0.9736
    },
    "top_features": [
      "dc_frac",
      "frac_fast",
      "active_days",
      "events_per_active_day",
      "n_devices",
      "delta_median",
      "n_asns",
      "max_events_1h",
      "n_events",
      "chat_frac",
      "success_rate",
      "night_frac",
      "n_countries",
      "mean_prompt_len",
      "timing_entropy"
    ]
  },
  "seq": {
    "classes": [
      "account_farmer",
      "normal",
      "prompt_sprayer",
      "spam_bot",
      "token_thief"
    ],
    "per_class_pr_auc": {
      "account_farmer": 0.9997,
      "normal": 0.9998,
      "prompt_sprayer": 1.0,
      "spam_bot": 0.9906,
      "token_thief": 1.0
    },
    "abuse_pr_auc": 0.997,
    "ato_anomaly_auc": 0.91,
    "ato_localization_median_hours": 41.77
  },
  "gnn": {
    "classes": [
      "account_farmer",
      "normal",
      "prompt_sprayer",
      "spam_bot",
      "token_thief"
    ],
    "per_class_pr_auc": {
      "account_farmer": 1.0,
      "normal": 0.9979,
      "prompt_sprayer": 0.8524,
      "spam_bot": 0.9819,
      "token_thief": 0.9997
    },
    "abuse_pr_auc": 0.9672,
    "abuse_pr_auc_by_evasion": {
      "0.00-0.33": 0.986,
      "0.33-0.66": 0.9632,
      "0.66-1.01": 0.9315
    }
  },
  "rings": {
    "precision": 0.7916,
    "recall": 0.752,
    "flagged": 950,
    "ip_fanout_cap": 10,
    "min_component": 5
  },
  "spray": {
    "cluster_truth_purity": 0.96,
    "precision": 0.7227,
    "recall": {
      "prompt_sprayer": 0.995,
      "spam_bot": 0.7267,
      "normal": 0.0,
      "prompt_sprayer_slow(e>0.6)": 0.9877
    }
  },
  "fusion": {
    "abuse_pr_auc": {
      "fused": 0.9886,
      "xgb_abuse": 0.9876,
      "seq_abuse": 0.9895,
      "gnn_abuse": 0.9851
    },
    "fused_by_evasion": {
      "0.00-0.33": 0.9689,
      "0.33-0.66": 0.9744,
      "0.66-1.01": 0.9759
    },
    "fusion_weights": {
      "xgb_abuse": -0.757,
      "seq_abuse": 1.834,
      "seq_anomaly": 0.558,
      "gnn_abuse": 2.032,
      "ring_flag": -0.496,
      "spray_sig": -0.116,
      "comp_size": 0.974,
      "seq_missing": 0.04
    },
    "tiers": {
      "suspend": {
        "n": 223,
        "abusive": 219,
        "precision": 0.982
      },
      "challenge": {
        "n": 43,
        "abusive": 15,
        "precision": 0.349
      },
      "rate_limit": {
        "n": 109,
        "abusive": 0,
        "precision": 0.0
      },
      "monitor": {
        "n": 2625,
        "abusive": 1,
        "precision": 0.0
      }
    },
    "expected_cost": 705.0,
    "cost_do_nothing": 8775.0
  }
}